BronkzTech/__init__.py
BronkzTech/client.py
bronkztech-1.0.4.dist-info/METADATA
bronkztech-1.0.4.dist-info/WHEEL
bronkztech-1.0.4.dist-info/top_level.txt
bronkztech-1.0.4.dist-info/RECORD
