Metadata-Version: 2.4
Name: BronkzTech
Version: 1.0.4
Summary: Cliente para a API da BronkzTech usando token
Home-page: https://discord.gg/MJ5qfSqRy8
Author: Dran
Requires-Python: >=3.9
Requires-Dist: requests>=2.32.0
Dynamic: author
Dynamic: home-page
Dynamic: requires-dist
Dynamic: requires-python
Dynamic: summary
